spherogram/presentations.py
spherogram/test_helper.py
spherogram/version.py
spherogram/__init__.py
spherogram/sage_helper.py
spherogram/test.py
spherogram/planarity.cpython-310-darwin.so
spherogram/graphs.py
spherogram/planarmap.cpython-310-darwin.so
spherogram/codecs/Base64LikeDT.py
spherogram/codecs/DT.py
spherogram/codecs/__init__.py
spherogram/links/simplify.py
spherogram/links/links_base.py
spherogram/links/doc.pdf
spherogram/links/torus.py
spherogram/links/bridge_bound.py
spherogram/links/exhaust.py
spherogram/links/__init__.py
spherogram/links/links.py
spherogram/links/twist.py
spherogram/links/extra_tests.py
spherogram/links/jones_old.py
spherogram/links/planar_isotopy.py
spherogram/links/seifert.py
spherogram/links/nx_helper.py
spherogram/links/orthogonal.py
spherogram/links/random_links.py
spherogram/links/alexander.py
spherogram/links/morse.py
spherogram/links/tangles.py
spherogram/links/ordered_set.py
spherogram/links/draw.py
spherogram/links/invariants.py
spherogram/links/jones.py
spherogram/links/test/test_montesinos.py
spherogram/links/test/__init__.py
spherogram/links/test/old_testing_code.py
spherogram/links/bands/regression.py
spherogram/links/bands/__init__.py
spherogram/links/bands/core.py
spherogram/links/bands/merge_links.py
spherogram/links/bands/search.py
spherogram/dev/dt_tests.py
spherogram/dev/dt_issue.py
spherogram/dev/sage_graph.py
spherogram/dev/sage_link_compare.py
spherogram/dev/__init__.py
spherogram/dev/issue_35.py
spherogram/dev/conventions.py
spherogram/dev/other_link_formats.py
spherogram/dev/hard_links.py
spherogram/dev/signature.py
spherogram/dev/tangle_patch.py
spherogram/dev/DTcodes.py
spherogram/dev/dev_jennet/AlexanderKauffman.py
spherogram/dev/dev_jennet/bridge_finding.py
spherogram/dev/dev_jennet/__init__.py
spherogram/dev/dev_jennet/spanning_trees.py
spherogram/dev/dev_jennet/test_links.py
spherogram-2.4.dist-info/RECORD
spherogram-2.4.dist-info/WHEEL
spherogram-2.4.dist-info/top_level.txt
spherogram-2.4.dist-info/METADATA
