Metadata-Version: 2.1
Name: spherogram
Version: 2.4
Summary: Spherical diagrams for 3-manifold topology
Home-page: https://github.com/3-manifolds/Spherogram
Author: Marc Culler and Nathan M. Dunfield
Author-email: culler@marc-culler.info, nathan@dunfield.info
License: GPLv2+
Keywords: knot,link,SnapPy
Classifier: Development Status :: 5 - Production/Stable
Classifier: Intended Audience :: Science/Research
Classifier: License :: OSI Approved :: GNU General Public License v2 or later (GPLv2+)
Classifier: Operating System :: OS Independent
Classifier: Programming Language :: C
Classifier: Programming Language :: Python
Classifier: Topic :: Scientific/Engineering :: Mathematics
Requires-Python: >=3
Requires-Dist: decorator
Requires-Dist: networkx
Requires-Dist: packaging
Requires-Dist: snappy-manifolds>=1.4
Requires-Dist: knot-floer-homology>=1.2.2
